{
  "project_info": {
    "project_number": "491933642026",
    "project_id": "moto-route-347312",
    "storage_bucket": "moto-route-347312.appspot.com"
  },
  "client": [
    {
      "client_info": {
        "mobilesdk_app_id": "1:491933642026:android:850f0e05966ba6a9810253",
        "android_client_info": {
          "package_name": "com.moto_route"
        }
      },
      "oauth_client": [
        {
          "client_id": "491933642026-7qmeb12f1r491gj5uon5fko94ur9sqbu.apps.googleusercontent.com",
          "client_type": 1,
          "android_info": {
            "package_name": "com.moto_route",
            "certificate_hash": "5e8f16062ea3cd2c4a0d547876baa6f38cabf625"
          }
        },
        {
          "client_id": "491933642026-opje85vktm998n6kk3hefetogq9o2792.apps.googleusercontent.com",
          "client_type": 3
        }
      ],
      "api_key": [
        {
          "current_key": "AIzaSyCPm1Nu8eOU8SJbNeLT-m6uyMAisS_dfk4"
        }
      ],
      "services": {
        "appinvite_service": {
          "other_platform_oauth_client": [
            {
              "client_id": "491933642026-opje85vktm998n6kk3hefetogq9o2792.apps.googleusercontent.com",
              "client_type": 3
            }
          ]
        }
      }
    }
  ],
  "configuration_version": "1"
}
